cloudgaze_cli/__init__.py
cloudgaze_cli/__main__.py
cloudgaze_cli-1.0.1.dist-info/METADATA
cloudgaze_cli-1.0.1.dist-info/WHEEL
cloudgaze_cli-1.0.1.dist-info/entry_points.txt
cloudgaze_cli-1.0.1.dist-info/top_level.txt
cloudgaze_cli-1.0.1.dist-info/RECORD
