Metadata-Version: 2.1
Name: cloudgaze-cli
Version: 1.0.1
Summary: Convert CloudFormation templates to draw.io compatible diagrams, with dependency arrows
Home-page: https://cloudgaze.readthedocs.io/en/latest/
Author: hawry
Author-email: hawry@hawry.net
License: MIT
Platform: UNKNOWN
Classifier: Programming Language :: Python :: 3
Classifier: Programming Language :: Python :: 3.7
Classifier: Programming Language :: Python :: 3.8
Classifier: Intended Audience :: Developers
Classifier: Intended Audience :: Information Technology
Classifier: Topic :: Software Development
Classifier: Topic :: Software Development :: Documentation
Requires-Dist: click (>=7.0)
